setup.py
jenkins_job_builder_brakeman/__init__.py
jenkins_job_builder_brakeman.egg-info/PKG-INFO
jenkins_job_builder_brakeman.egg-info/SOURCES.txt
jenkins_job_builder_brakeman.egg-info/dependency_links.txt
jenkins_job_builder_brakeman.egg-info/entry_points.txt
jenkins_job_builder_brakeman.egg-info/requires.txt
jenkins_job_builder_brakeman.egg-info/top_level.txt
jenkins_job_builder_brakeman/modules/__init__.py
jenkins_job_builder_brakeman/modules/publishers.py