Metadata-Version: 1.1
Name: jenkins-job-builder-brakeman
Version: 0.1
Summary: A jenkins job builder plugin to allow enabling Brakeman
Home-page: http://github.com/garethr/jenkins-job-builder-brakeman
Author: Gareth Rushgrove
Author-email: gareth@morethanseven.net
License: OSI
Keywords: jenkins,brakeman
Platform: UNKNOWN
Classifier: Development Status :: 3 - Alpha
Classifier: Intended Audience :: Developers
Classifier: License :: OSI Approved :: Apache Software License
Classifier: Natural Language :: English
Classifier: Topic :: System :: Systems Administration
Classifier: Operating System :: OS Independent
Classifier: Programming Language :: Python
